{ 
  "login":{
    "token" : "abc123",
    "user" : {
      "id": 1,
      "username": "MockUsername",
      "email": "MockEmail",
      "leagueId": 1,
      "episodes": {
        "characterForeignKeyId": [ 1, 2, 3, 17, 18, 19]
      }
    },
    "league":{
      "leagueId":1,
      "name":"MockLeagueName",
      "creatorId": 1,
      "members" : [1,2,3,4,5]
    },
    "characters":[
      {
        "firstName": "Cersei",
        "lastName": "Lannister",
        "house": "Lannister",
        "id": "1",
        "drafted": "null"
      },
      {
        "firstName": "Tyrion",
        "lastName": "Lannister",
        "house": "Lannister",
        "id": "2",
        "drafted": "null"
      },
      {
        "firstName": "Arya",
        "lastName": "Stark",
        "house": "Stark",
        "id": "3",
        "drafted": "null"
      },
      {
        "firstName": "Daenerys",
        "lastName": "Targaryen",
        "house": "Targaryen",
        "id": "4",
        "drafted": "null"
      },
      {
        "firstName": "Rodrik",
        "lastName": "Cassel",
        "house": "Stark",
        "id": "5",
        "drafted": "null"
      }
    ],
    "events":[
      {
        "id": 1,
        "type": "attendance",
        "description": "Arya showed up",
        "episodeId": 1,
        "points": 1
      },
      {
        "id": 2,
        "type": "Deceive someone you're sleeping with",
        "description": "Cercei sleeps with every man in castle, lies to Jamie",
        "episodeId": 2,
        "points": 35
      },
      {
        "id": 3,
        "type": "Surprise magic use",
        "description": "Quaiburn works on the mountain",
        "episodeId": 3,
        "points": 50
      }
    ]
  },
  "users":[
    {
      "id": 1,
      "username": "MockUsername",
      "email": "MockEmail",
      "leagueId": 1,
      "episodes": {
        "characterForeignKeyId": [ 1, 2, 3]
      }
    },
    {
      "id": 2,
      "username": "MockUsername2",
      "email": "MockEmail2",
      "leagueId": 1,
      "episodes": {
        "characterForeignKeyId": [4,5]
      }
    }
  ],
  "leagues":[
    {
      "leagueId":1,
      "name":"MockLeagueName",
      "creatorId": 1,
      "members" : [1,2]
    }
  ],
  "characters":[
    {
      "id": "1",
      "firstName": "Cersei",
      "lastName": "Lannister",
      "house": "Lannister",
      "drafted": "null"
    },
    {
      "id": "2",
      "firstName": "Tyrion",
      "lastName": "Lannister",
      "house": "Lannister",
      "drafted": "null"
    },
    {
      "id": "3",
      "firstName": "Arya",
      "lastName": "Stark",
      "house": "Stark",
      "drafted": "null"
    },
    {
      "id": "4",
      "firstName": "Daenerys",
      "lastName": "Targaryen",
      "house": "Targaryen",
      "drafted": "null"
    },
    {
      "id": "5",
      "firstName": "Rodrik",
      "lastName": "Cassel",
      "house": "Stark",
      "drafted": "null"
    }
  ],
  "events":[
    {
      "id": 1,
      "type": "attendance",
      "description": "Arya showed up",
      "episodeId": 1, 
      "character": 3,
      "points": 1
    },
    {
      "id": 2,
      "type": "Deceive someone you're sleeping with",
      "description": "Cercei sleeps with every man in castle, lies to Jamie",
      "episodeId": 2, 
      "character": 1,
      "points": 35
    },
    {
      "id": 3,
      "type": "Surprise magic use",
      "description": "hatched dragons",
      "episodeId": 3, 
      "character": 4,
      "points": 50
    }
  ]
}
